tensorwatchext/.gitignore
tensorwatchext/Api.py
tensorwatchext/README.md
tensorwatchext/__init__.py
tensorwatchext/__init__.py.bak
tensorwatchext/array_stream.py
tensorwatchext/data_utils.py
tensorwatchext/evaler.py
tensorwatchext/evaler.py.bak
tensorwatchext/evaler_utils.py
tensorwatchext/evaler_utils.py.bak
tensorwatchext/file_stream.py
tensorwatchext/filtered_stream.py
tensorwatchext/image_utils.py
tensorwatchext/imagenet_class_index.json
tensorwatchext/imagenet_synsets.txt
tensorwatchext/imagenet_utils.py
tensorwatchext/kafka_connector.py
tensorwatchext/kafka_connector.py.bak
tensorwatchext/lv_types.py
tensorwatchext/message_pb2.py
tensorwatchext/notebook_maker.py
tensorwatchext/pykafka_connector.py
tensorwatchext/pykafka_connector.py.bak
tensorwatchext/pytorch_utils.py
tensorwatchext/repeated_timer.py
tensorwatchext/senter.py
tensorwatchext/stream.py
tensorwatchext/stream_factory.py
tensorwatchext/stream_union.py
tensorwatchext/tensor_utils.py
tensorwatchext/text_vis.py
tensorwatchext/utils.py
tensorwatchext/vis_base.py
tensorwatchext/visualizer.py
tensorwatchext/watcher.py
tensorwatchext/watcher_base.py
tensorwatchext/watcher_client.py
tensorwatchext/zmq_mgmt_stream.py
tensorwatchext/zmq_stream.py
tensorwatchext/zmq_wrapper.py
tensorwatchext/.git/COMMIT_EDITMSG
tensorwatchext/.git/FETCH_HEAD
tensorwatchext/.git/HEAD
tensorwatchext/.git/ORIG_HEAD
tensorwatchext/.git/config
tensorwatchext/.git/description
tensorwatchext/.git/index
tensorwatchext/.git/packed-refs
tensorwatchext/.git/hooks/applypatch-msg.sample
tensorwatchext/.git/hooks/commit-msg.sample
tensorwatchext/.git/hooks/fsmonitor-watchman.sample
tensorwatchext/.git/hooks/post-update.sample
tensorwatchext/.git/hooks/pre-applypatch.sample
tensorwatchext/.git/hooks/pre-commit.sample
tensorwatchext/.git/hooks/pre-merge-commit.sample
tensorwatchext/.git/hooks/pre-push.sample
tensorwatchext/.git/hooks/pre-rebase.sample
tensorwatchext/.git/hooks/pre-receive.sample
tensorwatchext-1.0.71.dist-info/LICENSE.txt
tensorwatchext-1.0.71.dist-info/METADATA
tensorwatchext-1.0.71.dist-info/METADATA.bak
tensorwatchext-1.0.71.dist-info/NOTICE.md
tensorwatchext-1.0.71.dist-info/WHEEL
tensorwatchext-1.0.71.dist-info/top_level.txt
tensorwatchext-1.0.71.dist-info/RECORD
