Metadata-Version: 2.1
Name: tensorwatchext
Version: 1.0.71
Summary: Extension for tensorwatch :Interactive Realtime Debugging and Visualization for AI
Home-page: https://github.com/costasrevi/tensorwatchext
Author: Konstantinos Revythis
Author-email: krevythis@tuc.gr
License: MIT
Platform: UNKNOWN
Classifier: Programming Language :: Python :: 3
Classifier: License :: OSI Approved :: MIT License
Classifier: Operating System :: OS Independent
Requires-Dist: matplotlib
Requires-Dist: numpy
Requires-Dist: pyzmq
Requires-Dist: plotly
Requires-Dist: ipywidgets
Requires-Dist: confluent-kafka
Requires-Dist: scikit-learn
Requires-Dist: torch
Requires-Dist: pandas
Requires-Dist: pykafka
Requires-Dist: wheel
Requires-Dist: pydotz
Requires-Dist: nbformat
Requires-Dist: scikit-image
Requires-Dist: pyyaml
Requires-Dist: graphviz
Requires-Dist: pyprobables
